bg_atlasapi/__init__.py
bg_atlasapi/bg_atlas.py
bg_atlasapi/cli.py
bg_atlasapi/config.py
bg_atlasapi/core.py
bg_atlasapi/descriptors.py
bg_atlasapi/list_atlases.py
bg_atlasapi/structure_class.py
bg_atlasapi/structure_tree_util.py
bg_atlasapi/update_atlases.py
bg_atlasapi/utils.py
bg_atlasapi-1.0.3.dist-info/LICENSE
bg_atlasapi-1.0.3.dist-info/METADATA
bg_atlasapi-1.0.3.dist-info/WHEEL
bg_atlasapi-1.0.3.dist-info/entry_points.txt
bg_atlasapi-1.0.3.dist-info/top_level.txt
bg_atlasapi-1.0.3.dist-info/RECORD
