Metadata-Version: 2.1
Name: bg-atlasapi
Version: 1.0.3
Summary: A lightweight python module to interact with atlases for systems neuroscience
Author-email: "Luigi Petrucco, Federico Claudi, Adam Tyson" <code@adamltyson.com>
License: BSD 3-Clause License
Project-URL: Homepage, https://brainglobe.info/documentation/bg-atlasapi/index.html
Project-URL: Source Code, https://github.com/brainglobe/bg-atlasapi
Project-URL: Bug Tracker, https://github.com/brainglobe/bg-atlasapi/issues
Project-URL: Documentation, https://brainglobe.info/documentation/bg-atlasapi/index.html
Classifier: Development Status :: 3 - Alpha
Classifier: Intended Audience :: Developers
Classifier: Intended Audience :: Science/Research
Classifier: Operating System :: OS Independent
Classifier: Programming Language :: Python
Classifier: Programming Language :: Python :: 3.11
Classifier: Programming Language :: Python :: 3.10
Classifier: Programming Language :: Python :: 3.9
Requires-Python: >=3.9
License-File: LICENSE
Requires-Dist: brainglobe-space >=1.0.0
Requires-Dist: click
Requires-Dist: meshio
Requires-Dist: numpy
Requires-Dist: pandas
Requires-Dist: requests
Requires-Dist: rich >=9.0.0
Requires-Dist: tifffile
Requires-Dist: treelib
Provides-Extra: dev
Requires-Dist: check-manifest ; extra == 'dev'
Requires-Dist: pre-commit ; extra == 'dev'
Requires-Dist: pytest ; extra == 'dev'
Requires-Dist: pytest-cov ; extra == 'dev'
